{
  "portraitScale": 1,
  "portraitTranslation": [0, 0, 0],
  "profileScale": 1,
  "profileTranslation": [0, 0, 0],
  "poses": {
    "anti-condition": {
      "poseName": "anti-condition",
      "condition": "!q.is_standing_on_blocks(1, 'minecraft:gravel', 'minecraft:suspicious_gravel', 'minecraft:suspicious_sand', 'minecraft:packed_mud', 'minecraft:grass_block', 'minecraft:sand', 'minecraft:red_sand', 'minecraft:dirt', 'minecraft:coarse_dirt', 'minecraft:podzol', 'minecraft:mycelium', 'minecraft:rooted_dirt', 'minecraft:mud', 'minecraft:moss_block', 'minecraft:muddy_mangrove_roots')",
      "poseTypes": ["STAND", "WALK", "NONE", "PORTRAIT", "PROFILE", "FLOAT", "HOVER", "FLY"],
      "animations": [
        "q.bedrock('rustling_spot', 'blank')"
      ]
    },
    "grass": {
      "poseName": "grass",
      "condition": "q.is_standing_on_blocks(1, 'minecraft:grass_block', 'minecraft:moss_block')",
      "poseTypes": ["STAND", "WALK", "NONE", "PORTRAIT", "PROFILE", "FLOAT", "HOVER", "FLY"],
      "animations": [
        "q.bedrock('rustling_spot', 'grass')"
      ]
    },
    "dirt": {
      "poseName": "dirt",
      "condition": "q.is_standing_on_blocks(1, 'minecraft:dirt', 'minecraft:coarse_dirt', 'minecraft:podzol', 'minecraft:mycelium', 'minecraft:rooted_dirt', 'minecraft:mud', 'minecraft:muddy_mangrove_roots')",
      "poseTypes": ["STAND", "WALK", "NONE", "PORTRAIT", "PROFILE", "FLOAT", "HOVER", "FLY"],
      "animations": [
        "q.bedrock('rustling_spot', 'dirt')"
      ]
    },
    "sand": {
      "poseName": "sand",
      "condition": "q.is_standing_on_blocks(1, 'minecraft:sand', 'minecraft:red_sand', 'minecraft:sandstone', 'minecraft:red_sandstone', 'minecraft:suspicious_sand')",
      "poseTypes": ["STAND", "WALK", "NONE", "PORTRAIT", "PROFILE", "FLOAT", "HOVER", "FLY"],
      "animations": [
        "q.bedrock('rustling_spot', 'sand')"
      ]
    },
    "red_sand": {
      "poseName": "red_sand",
      "condition": "q.is_standing_on_blocks(1, 'minecraft:red_sand', 'minecraft:red_sandstone')",
      "poseTypes": ["STAND", "WALK", "NONE", "PORTRAIT", "PROFILE", "FLOAT", "HOVER", "FLY"],
      "animations": [
        "q.bedrock('rustling_spot', 'red_sand')"
      ]
    },
    "gravel": {
      "poseName": "gravel",
      "condition": "q.is_standing_on_blocks(1, 'minecraft:gravel', 'minecraft:suspicious_gravel')",
      "poseTypes": ["STAND", "WALK", "NONE", "PORTRAIT", "PROFILE", "FLOAT", "HOVER", "FLY"],
      "animations": [
        "q.bedrock('rustling_spot', 'gravel')"
      ]
    }
  }
}